Workbook

Sheet Executive Summary & P&L
A1: SOLOSPIDER & RANK MONK — FINANCIAL MODEL & P&L PROJECTION
A2: SaaS Economics, Unit Margin Breakdown, Feature COGS (Media Studio AI & SEO), and Pro-Forma Cash Flow
A4: TARGET MRR (M12) | C4: GROSS MARGIN % | D4: BLENDED ARPU | E4: NET PROFIT MARGIN | F4: ANNUAL RUN-RATE (ARR) | G4: BREAK-EVEN USERS
A5: ='12-Month Pro-Forma'!E15 | C5: ='12-Month Pro-Forma'!G15 | D5: ='Unit Economics & Tiers'!G12 | E5: ='12-Month Pro-Forma'!K15 | F5: ='12-Month Pro-Forma'!E15*12 | G5: =ROUNDUP('Fixed OpEx'!D17/'Unit Economics & Tiers'!F12, 0)
A8: CONSOLIDATED EXECUTIVE P&L STATEMENT (STEADY-STATE SCALE)
A9: Financial Metric / Line Item | B9: Starter Tier | C9: Growth Tier | D9: Scale Tier | E9: Enterprise / Custom | F9: Blended Steady-State | G9: Notes & Method
A10: Subscription Price / ARPU | B10: ='Unit Economics & Tiers'!C6 | C10: ='Unit Economics & Tiers'!C7 | D10: ='Unit Economics & Tiers'!C8 | E10: ='Unit Economics & Tiers'!C9 | F10: ='Unit Economics & Tiers'!G12 | G10: Direct model formula
A11: Monthly Active Subscribers Mix | B11: 20% | C11: 50% | D11: 25% | E11: 5% | F11: 100% | G11: Direct model formula
A12: Monthly Gross Revenue / User | B12: ='Unit Economics & Tiers'!C6 | C12: ='Unit Economics & Tiers'!C7 | D12: ='Unit Economics & Tiers'!C8 | E12: ='Unit Economics & Tiers'!C9 | F12: ='Unit Economics & Tiers'!G12 | G12: Direct model formula
A13: Variable AI & API COGS / User | B13: ='Unit Economics & Tiers'!D6 | C13: ='Unit Economics & Tiers'!D7 | D13: ='Unit Economics & Tiers'!D8 | E13: ='Unit Economics & Tiers'!D9 | F13: ='Unit Economics & Tiers'!D12 | G13: Direct model formula
A14: Payment Gateway Fees (2% + $0.30) | B14: =B12*0.02+0.3 | C14: =C12*0.02+0.3 | D14: =D12*0.02+0.3 | E14: =E12*0.02+0.3 | F14: =F12*0.02+0.3 | G14: Direct model formula
A15: Total Direct Cost per User | B15: =B13+B14 | C15: =C13+C14 | D15: =D13+D14 | E15: =E13+E14 | F15: =F13+F14 | G15: Direct model formula
A16: Gross Margin Contribution ($) | B16: =B12-B15 | C16: =C12-C15 | D16: =D12-D15 | E16: =E12-E15 | F16: =F12-F15 | G16: Direct model formula
A17: Gross Margin Contribution (%) | B17: =B16/IF(B12=0,1,B12) | C17: =C16/C12 | D17: =D16/D12 | E17: =E16/E12 | F17: =F16/F12 | G17: Direct model formula
A18: Allocated Fixed OpEx / User (at 300 users) | B18: ='Fixed OpEx'!D17/300 | C18: ='Fixed OpEx'!D17/300 | D18: ='Fixed OpEx'!D17/300 | E18: ='Fixed OpEx'!D17/300 | F18: ='Fixed OpEx'!D17/300 | G18: Fixed server + infra base divided across customer cohort
A19: Net Operating Profit per User ($) | B19: =B16-B18 | C19: =C16-C18 | D19: =D16-D18 | E19: =E16-E18 | F19: =F16-F18 | G19: Direct model formula
A20: Net Operating Margin (%) | B20: =B19/IF(B12=0,1,B12) | C20: =C19/C12 | D20: =D19/D12 | E20: =E19/E12 | F20: =F19/F12 | G20: Direct model formula
A22: BUSINESS SENSITIVITY & COHORT SCENARIO ANALYSIS
A23: Scenario Name | B23: Active Paid Users | C23: Blended MRR | D23: Monthly Variable COGS | E23: Fixed Monthly OpEx | F23: Monthly Net EBITDA | G23: Annual Net Profit
A24: Conservative (Early Traction) | B24: 50 | C24: =B24*'Unit Economics & Tiers'!G12 | D24: =B24*'Unit Economics & Tiers'!D12 | E24: ='Fixed OpEx'!D17 | F24: =C24-D24-E24 | G24: =F24*12
A25: Target Baseline (Scale Spider) | B25: 250 | C25: =B25*'Unit Economics & Tiers'!G12 | D25: =B25*'Unit Economics & Tiers'!D12 | E25: ='Fixed OpEx'!D17 | F25: =C25-D25-E25 | G25: =F25*12
A26: Aggressive Growth (500 Subscribers) | B26: 500 | C26: =B26*'Unit Economics & Tiers'!G12 | D26: =B26*'Unit Economics & Tiers'!D12 | E26: ='Fixed OpEx'!D17*1.2 | F26: =C26-D26-E26 | G26: =F26*12
A27: Enterprise / Market Leader (1,000 Subs) | B27: 1000 | C27: =B27*'Unit Economics & Tiers'!G12 | D27: =B27*'Unit Economics & Tiers'!D12 | E27: ='Fixed OpEx'!D17*1.5 | F27: =C27-D27-E27 | G27: =F27*12

Sheet Feature Cost Matrix (COGS)
A1: GRANULAR FEATURE COST BREAKDOWN & API COGS (SOLOSPIDER / RANK MONK)
A2: Complete unit costs per image generation, video generation, AI writing, AEO audits, and crawlers
A4: Module & Feature Component | B4: Provider / Engine Used | C4: Input / Specs / Resolution | D4: Unit Cost ($) | E4: Unit Cost (INR ₹) | F4: Billing Metric | G4: Technical Architecture & Fallback Strategy
A5: MEDIA STUDIO — AI IMAGE GENERATION (CORE REQUIREMENT)
A6: High-Quality Social Graphic | B6: Flux 2 Pro (OpenRouter) | C6: 1024x1024 PNG / JPG | D6: 0.04 | E6: =D6*88 | F6: Per generated image | G6: black-forest-labs/flux.2-pro via OpenRouter; Supabase upload
A7: Alternative / Fast Image Gen | B7: Stable Diffusion 3.5 / SDXL | C7: 1024x1024 / 1200x628 | D7: 0.02 | E7: =D7*88 | F7: Per generated image | G7: Replicate / Fal.ai high-speed render; 50% cheaper fallback
A8: Editorial Photorealistic Hero | B8: DALL-E 3 HD (OpenAI) | C8: 1792x1024 Banner | D8: 0.08 | E8: =D8*88 | F8: Per high-def banner | G8: Used for long-form featured blog headers with brand text
A9: Free / Batch Preview Graphic | B9: Pollinations AI | C9: 1080x1080 WebP | D9: 0 | E9: =D9*88 | F9: Per preview render | G9: Zero-cost real-time canvas preview before user finalizes render
A10: Image Storage & CDN Bandwidth | B10: Supabase Storage / Cloudflare R2 | C10: 3 MB average per PNG | D10: 0.001 | E10: =D10*88 | F10: Per image stored / served | G10: Cloudflare R2 zero-egress bucket, Supabase blog_images storage
A11: MEDIA STUDIO — AI VIDEO GENERATION (CORE REQUIREMENT)
A12: AI Motion Reel / Short Video | B12: Alibaba Wan 2.6 (OpenRouter) | C12: 5 Seconds, 1080p, 16:9 / 9:16 | D12: 0.18 | E12: =D12*88 | F12: Per 5-second video | G12: Native OpenRouter alibaba/wan-2.6; auto-saved to Supabase MP4
A13: High-Fidelity Cinematic Clip | B13: Runway Gen-3 Alpha / Luma | C13: 5 Seconds, 720p/1080p | D13: 0.35 | E13: =D13*88 | F13: Per generation | G13: Premium motion synthesis via Replicate / Fal.ai endpoint
A14: Short Promo B-Roll Video | B14: Kling AI / Minimax Hailuo | C14: 5-6 Seconds, 1080p | D14: 0.22 | E14: =D14*88 | F14: Per clip | G14: Used for social Instagram Reels, TikTok, and YouTube Shorts
A15: Public B2B Fallback Video | B15: GitHub Raw / Video Templates | C15: Pre-rendered HD Loops | D15: 0 | E15: =D15*88 | F15: Per fallback clip | G15: Immediate zero-cost preview if external video API is rate-limited
A16: Video CDN Hosting & Transcoding | B16: Cloudflare Stream / R2 | C16: 15 MB average MP4 | D16: 0.005 | E16: =D16*88 | F16: Per video streamed | G16: Adaptive bitrate streaming and persistent media storage
A17: CONTENT ENGINE — AI BLOG & LONG-FORM ARTICLES
A18: Full Long-Form Blog Article | B18: Gemini 2.5 Flash (OpenRouter) | C18: 2,500 words, Schema, FAQs | D18: 0.004 | E18: =D18*88 | F18: Per complete article | G18: Primary low-latency generator; high EEAT structured markup
A19: Deep Research / Premium Article | B19: Claude 3.5 Sonnet / GPT-4o | C19: 3,500 words with citations | D19: 0.038 | E19: =D19*88 | F19: Per premium article | G19: Used for competitive ranking content and thought leadership
A20: Meta Title & Description Batch | B20: OpenRouter Gemini Flash | C20: 10 Variations per post | D20: 0.0005 | E20: =D20*88 | F20: Per batch generate | G20: Auto-optimized for Google CTR and character truncation rules
A21: Schema JSON-LD & FAQ Builder | B21: OpenRouter Gemini Flash | C21: Article + FAQPage + Breadcrumb | D21: 0.0008 | E21: =D21*88 | F21: Per schema bundle | G21: Self-validating schema structure injected into Next.js/WP
A22: AEO / GEO CITATION RADAR (AI ENGINE PROMPT MONITORING)
A23: Perplexity Sonar Prompt Audit | B23: Perplexity Sonar Online | C23: Live web search query | D23: 0.005 | E23: =D23*88 | F23: Per query audit | G23: Scans brand citation, recommendation ranking, and source URLs
A24: ChatGPT Search Citation Check | B24: OpenAI GPT-4o Search | C24: Search ground truth audit | D24: 0.006 | E24: =D24*88 | F24: Per model audit | G24: Verifies whether ChatGPT answers recommend the client domain
A25: Gemini AI Overview Citation | B25: Gemini 2.5 Flash w/ Search | C25: Grounding enabled search | D25: 0.003 | E25: =D25*88 | F25: Per audit check | G25: Checks Google SGE / AI Overviews inclusion status
A26: Comprehensive Multi-Model Scan | B26: 4 Models Combined (Sonar, GPT, Gemini, Claude) | C26: Full brand prompt report | D26: 0.025 | E26: =D26*88 | F26: Per full radar scan | G26: Complete audit across all 4 top LLM engines simultaneously
A27: TECHNICAL SEO & COMPETITOR VOID SPY
A28: Full Site Health Crawl | B28: Custom Playwright + Apify Proxy | C28: 500-page deep crawl | D28: 0.045 | E28: =D28*88 | F28: Per crawl run | G28: Detects 404s, redirect chains, canonical errors, orphan pages
A29: SERP Rank & Keyword Position | B29: DataForSEO / SerpApi | C29: 100 Keywords tracking | D29: 0.02 | E29: =D29*88 | F29: Per 100 keywords | G29: Real-time Google mobile + desktop SERP ranking position
A30: Competitor Gap & Void Keyword | B30: DataForSEO SERP Intelligence | C30: Domain vs Domain matrix | D30: 0.035 | E30: =D30*88 | F30: Per competitor pull | G30: Finds keywords competitors rank for that client is missing
A31: Backlink Radar & Toxic Checker | B31: DataForSEO Backlink API | C31: Backlink profile audit | D31: 0.025 | E31: =D31*88 | F31: Per backlink pull | G31: Monitors lost backlinks, referring domains, toxic link spam
A32: SOCIAL CMS SYNC & PLATFORM DISTRIBUTION
A33: Multi-Platform Social Auto-Post | B33: Official APIs (Meta, LinkedIn, X) | C33: API Webhook trigger | D33: 0.0001 | E33: =D33*88 | F33: Per scheduled post | G33: Publishes to Instagram, Facebook, LinkedIn, Twitter, Pinterest
A34: Shopify & WordPress Live Sync | B34: Shopify GraphQL & WP REST API | C34: Direct webhooks & publishing | D34: 0.0001 | E34: =D34*88 | F34: Per blog sync | G34: Auto-publishes articles directly to client store/blog with tags

Sheet Unit Economics & Tiers
A1: SUBSCRIPTION TIERS & UNIT ECONOMICS PER SUBSCRIBER
A2: Detailed monthly usage allowances, direct COGS per user, gross margins, and LTV/CAC ratios
A4: Plan Tier Name | B4: Billing Cycle | C4: Monthly Price ($) | D4: Estimated Monthly COGS ($) | E4: Gross Contribution ($) | F4: Gross Margin (%) | G4: Target User Share (%)
A6: Starter Tier (Trial / Entry) | B6: Monthly | C6: 0 | D6: =D18 | E6: =C6-D6 | F6: =IF(C6=0, 0, E6/C6) | G6: 0.2
A7: Growth Tier (Core SMBs) | B7: Monthly | C7: 199 | D7: =D26 | E7: =C7-D7 | F7: =E7/C7 | G7: 0.5
A8: Scale Tier (Agencies & High Growth) | B8: Monthly | C8: 699 | D8: =D34 | E8: =C8-D8 | F8: =E8/C8 | G8: 0.25
A9: Custom / Enterprise Brand | B9: Monthly | C9: 1299 | D9: =D42 | E9: =C9-D9 | F9: =E9/C9 | G9: 0.05
A12: WEIGHTED BLENDED AVERAGE (ACROSS ALL PAID SUBSCRIBERS) | C12: =SUMPRODUCT(C6:C9, G6:G9) | D12: =SUMPRODUCT(D6:D9, G6:G9) | E12: =C12-D12 | F12: =E12/C12 | G12: =SUM(G6:G9)
A14: 1. STARTER PLAN ($0 / FREE TRIAL) — QUOTA & USAGE COST BREAKDOWN
A15: AI Blog Posts (5 per month) | B15: 5 | C15: ='Feature Cost Matrix (COGS)'!D18 | D15: =B15*C15 | E15: 5 Gemini Flash articles with basic schema
A16: Media Studio - AI Images (0 enabled) | B16: 0 | C16: ='Feature Cost Matrix (COGS)'!D6 | D16: =B16*C16 | E16: Media studio disabled on free tier
A17: Media Studio - AI Videos (0 enabled) | B17: 0 | C17: ='Feature Cost Matrix (COGS)'!D12 | D17: =B17*C17 | E17: Video studio disabled on free tier
A18: AEO Radar Prompt Audits (1 initial) | B18: 1 | C18: ='Feature Cost Matrix (COGS)'!D23 | D18: =B18*C18 | E18: One-time initial brand search test
A20: 2. GROWTH PLAN ($199 / MO) — CORE SMB USAGE & COST BREAKDOWN
A21: AI Long-Form Blog Articles (40 articles/mo) | B21: 40 | C21: ='Feature Cost Matrix (COGS)'!D18 | D21: =B21*C21 | E21: Gemini 2.5 Flash + Schema JSON-LD markup
A22: Media Studio — AI Images Generated (30 images/mo) | B22: 30 | C22: ='Feature Cost Matrix (COGS)'!D6 | D22: =B22*C22 | E22: Flux 2 Pro high-quality social graphics (1024x1024)
A23: Media Studio — AI Videos Generated (10 videos/mo) | B23: 10 | C23: ='Feature Cost Matrix (COGS)'!D12 | D23: =B23*C23 | E23: Wan 2.6 motion clips (5 seconds HD MP4)
A24: AEO / GEO Radar Audits (20 prompt scans/mo) | B24: 20 | C24: ='Feature Cost Matrix (COGS)'!D25 | D24: =B24*C24 | E24: Scans across Perplexity, ChatGPT, Gemini, Claude
A25: Technical Site Crawls (4 weekly audits) | B25: 4 | C25: ='Feature Cost Matrix (COGS)'!D28 | D25: =B25*C25 | E25: Weekly 500-page health scan + error detection
A26: SERP Keyword Tracking (250 keywords) | B26: 2.5 | C26: ='Feature Cost Matrix (COGS)'!D29 | D26: =B26*C26 | E26: DataForSEO tracking (2.5 units of 100 keywords)
A28: 3. SCALE PLAN ($699 / MO) — HIGH GROWTH & AGENCY COST BREAKDOWN
A29: AI Long-Form Blog Articles (150 articles/mo) | B29: 150 | C29: ='Feature Cost Matrix (COGS)'!D18 | D29: =B29*C29 | E29: Multi-brand content generation across 10 sites
A30: Media Studio — AI Images Generated (100 images/mo) | B30: 100 | C30: ='Feature Cost Matrix (COGS)'!D6 | D30: =B30*C30 | E30: Flux 2 Pro branded graphics & banners
A31: Media Studio — AI Videos Generated (35 videos/mo) | B31: 35 | C31: ='Feature Cost Matrix (COGS)'!D12 | D31: =B31*C31 | E31: Wan 2.6 / Runway motion clips for social & reels
A32: AEO / GEO Radar Audits (60 prompt scans/mo) | B32: 60 | C32: ='Feature Cost Matrix (COGS)'!D25 | D32: =B32*C32 | E32: Weekly brand visibility checks on all AI engines
A33: Technical Site Crawls (12 audits across projects) | B33: 12 | C33: ='Feature Cost Matrix (COGS)'!D28 | D33: =B33*C33 | E33: Deep crawling for 10 connected client domains
A34: SERP Keyword Tracking (1,000 keywords) | B34: 10 | C34: ='Feature Cost Matrix (COGS)'!D29 | D34: =B34*C34 | E34: 1,000 daily tracked keywords on Google mobile/desktop
A36: 4. CUSTOM / ENTERPRISE PLAN ($1,299 / MO) — HIGH VOLUME BREAKDOWN
A37: AI Long-Form Blog Articles (350 articles/mo) | B37: 350 | C37: ='Feature Cost Matrix (COGS)'!D18 | D37: =B37*C37 | E37: Enterprise scale editorial production
A38: Media Studio — AI Images Generated (250 images/mo) | B38: 250 | C38: ='Feature Cost Matrix (COGS)'!D6 | D38: =B38*C38 | E38: Full-scale visual asset production
A39: Media Studio — AI Videos Generated (80 videos/mo) | B39: 80 | C39: ='Feature Cost Matrix (COGS)'!D12 | D39: =B39*C39 | E39: Daily AI video campaigns for social platforms
A40: AEO / GEO Radar Audits (150 prompt scans/mo) | B40: 150 | C40: ='Feature Cost Matrix (COGS)'!D25 | D40: =B40*C40 | E40: Continuous automated prompt testing & alerts
A41: Technical Site Crawls (30 deep site audits) | B41: 30 | C41: ='Feature Cost Matrix (COGS)'!D28 | D41: =B41*C41 | E41: Unlimited site crawls + self-healing fixes
A42: SERP Keyword Tracking (2,500 keywords) | B42: 25 | C42: ='Feature Cost Matrix (COGS)'!D29 | D42: =B42*C42 | E42: 2,500 daily tracked search positions

Sheet Fixed OpEx
A1: MONTHLY FIXED OPERATIONAL EXPENSES (OPEX) BREAKDOWN
A2: Server Infrastructure, Databases, Dev Tools, Domains, SaaS Subscriptions, and Core Overhead
A4: Expense Category | B4: Vendor / Tool | C4: Purpose / Tier | D4: Monthly Cost ($) | E4: Monthly Cost (INR ₹) | F4: Cost Optimization / Scaling Notes
A5: Cloud Infrastructure | B5: Supabase Pro Plan | C5: PostgreSQL database, Auth, Storage bucket, Realtime | D5: 25 | E5: =D5*88 | F5: Base $25/mo covers 100k auth users and 8GB database
A6: Cloud Infrastructure | B6: Vercel Pro Team | C6: Next.js App hosting, edge functions, serverless compute | D6: 20 | E6: =D6*88 | F6: Base team seat; handles up to 1M monthly requests
A7: Cloud Infrastructure | B7: Cloudflare Pro & R2 | C7: DNS, DDoS protection, edge caching, image & video storage | D7: 25 | E7: =D7*88 | F7: Zero egress fees on R2 object storage saving massive video bandwidth
A8: Cloud Infrastructure | B8: Upstash Redis / BullMQ | C8: Background async queues for blog, video, and crawl jobs | D8: 15 | E8: =D8*88 | F8: Serverless Redis queue; pay-per-request scaling
A9: Cloud Infrastructure | B9: Resend / SendGrid | C9: Transactional emails, invite links, outreach pitches | D9: 20 | E9: =D9*88 | F9: Covers up to 50,000 monthly transactional emails
A10: Developer Tools | B10: GitHub Team | C10: Source control, GitHub Actions CI/CD automated build pipelines | D10: 8 | E10: =D10*88 | F10: Private repository hosting & automated tests
A11: Developer Tools | B11: Sentry / Error Tracking | C11: Application performance monitoring, crash diagnostics | D11: 29 | E11: =D11*88 | F11: Real-time production alerts on API failures or LLM errors
A12: Security & Domains | B12: Namecheap / Cloudflare | C12: Custom domains (solospider.ai, rankmonk.com), SSL certs | D12: 5 | E12: =D12*88 | F12: Annual domains amortized to monthly basis
A13: Customer Support | B13: Crisp / Intercom Chat | C13: In-app live customer support widget and ticketing | D13: 25 | E13: =D13*88 | F13: Direct messaging for user onboarding and troubleshooting
A14: Payment Gateway & Compliance | B14: Razorpay / Stripe | C14: Merchant account compliance, invoicing, tax compliance | D14: 10 | E14: =D14*88 | F14: Fixed monthly compliance & recurring billing tools
A15: Marketing Reserve | B15: Organic SEO & Social Ads | C15: CAC testing, directory listings, organic community growth | D15: 250 | E15: =D15*88 | F15: Bootstrap initial customer acquisition budget
A16: Contingency & Reserve | B16: Buffer / Float | C16: Unforeseen API spikes, surge token usage, cloud burst | D16: 100 | E16: =D16*88 | F16: Safety cushion against variable consumption spikes
A17: TOTAL MONTHLY FIXED OPEX (OVERHEAD) | D17: =SUM(D5:D16) | E17: =D17*88 | F17: Essential foundation for sustaining high-uptime production platform

Sheet 12-Month Pro-Forma
A1: 12-MONTH PRO-FORMA FINANCIAL FORECAST & CASH FLOW PROJECTION
A2: Month-by-month subscriber growth, gross revenue, direct API COGS, fixed overhead, and net cash flow
A4: Month | B4: Growth Users (50%) | C4: Scale Users (25%) | D4: Enterprise (5%) | E4: Total MRR ($) | F4: Variable COGS ($) | G4: Gross Margin (%) | H4: Fixed OpEx ($) | I4: Payment Gateway Fees | J4: Net Profit ($) | K4: Net Margin (%)
A5: Month 1 | B5: 10 | C5: 3 | D5: 0 | E5: =B5*'Unit Economics & Tiers'!C7 + C5*'Unit Economics & Tiers'!C8 + D5*'Unit Economics & Tiers'!C9 | F5: =B5*'Unit Economics & Tiers'!D7 + C5*'Unit Economics & Tiers'!D8 + D5*'Unit Economics & Tiers'!D9 | G5: =(E5-F5)/E5 | H5: ='Fixed OpEx'!D17 * IF(5>10, 1.3, IF(5>7, 1.15, 1.0)) | I5: =E5*0.02 + (B5+C5+D5)*0.3 | J5: =E5-F5-H5-I5 | K5: =J5/E5
A6: Month 2 | B6: 18 | C6: 6 | D6: 1 | E6: =B6*'Unit Economics & Tiers'!C7 + C6*'Unit Economics & Tiers'!C8 + D6*'Unit Economics & Tiers'!C9 | F6: =B6*'Unit Economics & Tiers'!D7 + C6*'Unit Economics & Tiers'!D8 + D6*'Unit Economics & Tiers'!D9 | G6: =(E6-F6)/E6 | H6: ='Fixed OpEx'!D17 * IF(6>10, 1.3, IF(6>7, 1.15, 1.0)) | I6: =E6*0.02 + (B6+C6+D6)*0.3 | J6: =E6-F6-H6-I6 | K6: =J6/E6
A7: Month 3 | B7: 30 | C7: 10 | D7: 1 | E7: =B7*'Unit Economics & Tiers'!C7 + C7*'Unit Economics & Tiers'!C8 + D7*'Unit Economics & Tiers'!C9 | F7: =B7*'Unit Economics & Tiers'!D7 + C7*'Unit Economics & Tiers'!D8 + D7*'Unit Economics & Tiers'!D9 | G7: =(E7-F7)/E7 | H7: ='Fixed OpEx'!D17 * IF(7>10, 1.3, IF(7>7, 1.15, 1.0)) | I7: =E7*0.02 + (B7+C7+D7)*0.3 | J7: =E7-F7-H7-I7 | K7: =J7/E7
A8: Month 4 | B8: 45 | C8: 16 | D8: 2 | E8: =B8*'Unit Economics & Tiers'!C7 + C8*'Unit Economics & Tiers'!C8 + D8*'Unit Economics & Tiers'!C9 | F8: =B8*'Unit Economics & Tiers'!D7 + C8*'Unit Economics & Tiers'!D8 + D8*'Unit Economics & Tiers'!D9 | G8: =(E8-F8)/E8 | H8: ='Fixed OpEx'!D17 * IF(8>10, 1.3, IF(8>7, 1.15, 1.0)) | I8: =E8*0.02 + (B8+C8+D8)*0.3 | J8: =E8-F8-H8-I8 | K8: =J8/E8
A9: Month 5 | B9: 65 | C9: 24 | D9: 3 | E9: =B9*'Unit Economics & Tiers'!C7 + C9*'Unit Economics & Tiers'!C8 + D9*'Unit Economics & Tiers'!C9 | F9: =B9*'Unit Economics & Tiers'!D7 + C9*'Unit Economics & Tiers'!D8 + D9*'Unit Economics & Tiers'!D9 | G9: =(E9-F9)/E9 | H9: ='Fixed OpEx'!D17 * IF(9>10, 1.3, IF(9>7, 1.15, 1.0)) | I9: =E9*0.02 + (B9+C9+D9)*0.3 | J9: =E9-F9-H9-I9 | K9: =J9/E9
A10: Month 6 | B10: 90 | C10: 35 | D10: 4 | E10: =B10*'Unit Economics & Tiers'!C7 + C10*'Unit Economics & Tiers'!C8 + D10*'Unit Economics & Tiers'!C9 | F10: =B10*'Unit Economics & Tiers'!D7 + C10*'Unit Economics & Tiers'!D8 + D10*'Unit Economics & Tiers'!D9 | G10: =(E10-F10)/E10 | H10: ='Fixed OpEx'!D17 * IF(10>10, 1.3, IF(10>7, 1.15, 1.0)) | I10: =E10*0.02 + (B10+C10+D10)*0.3 | J10: =E10-F10-H10-I10 | K10: =J10/E10
A11: Month 7 | B11: 125 | C11: 50 | D11: 6 | E11: =B11*'Unit Economics & Tiers'!C7 + C11*'Unit Economics & Tiers'!C8 + D11*'Unit Economics & Tiers'!C9 | F11: =B11*'Unit Economics & Tiers'!D7 + C11*'Unit Economics & Tiers'!D8 + D11*'Unit Economics & Tiers'!D9 | G11: =(E11-F11)/E11 | H11: ='Fixed OpEx'!D17 * IF(11>10, 1.3, IF(11>7, 1.15, 1.0)) | I11: =E11*0.02 + (B11+C11+D11)*0.3 | J11: =E11-F11-H11-I11 | K11: =J11/E11
A12: Month 8 | B12: 170 | C12: 70 | D12: 8 | E12: =B12*'Unit Economics & Tiers'!C7 + C12*'Unit Economics & Tiers'!C8 + D12*'Unit Economics & Tiers'!C9 | F12: =B12*'Unit Economics & Tiers'!D7 + C12*'Unit Economics & Tiers'!D8 + D12*'Unit Economics & Tiers'!D9 | G12: =(E12-F12)/E12 | H12: ='Fixed OpEx'!D17 * IF(12>10, 1.3, IF(12>7, 1.15, 1.0)) | I12: =E12*0.02 + (B12+C12+D12)*0.3 | J12: =E12-F12-H12-I12 | K12: =J12/E12
A13: Month 9 | B13: 225 | C13: 95 | D13: 11 | E13: =B13*'Unit Economics & Tiers'!C7 + C13*'Unit Economics & Tiers'!C8 + D13*'Unit Economics & Tiers'!C9 | F13: =B13*'Unit Economics & Tiers'!D7 + C13*'Unit Economics & Tiers'!D8 + D13*'Unit Economics & Tiers'!D9 | G13: =(E13-F13)/E13 | H13: ='Fixed OpEx'!D17 * IF(13>10, 1.3, IF(13>7, 1.15, 1.0)) | I13: =E13*0.02 + (B13+C13+D13)*0.3 | J13: =E13-F13-H13-I13 | K13: =J13/E13
A14: Month 10 | B14: 290 | C14: 125 | D14: 15 | E14: =B14*'Unit Economics & Tiers'!C7 + C14*'Unit Economics & Tiers'!C8 + D14*'Unit Economics & Tiers'!C9 | F14: =B14*'Unit Economics & Tiers'!D7 + C14*'Unit Economics & Tiers'!D8 + D14*'Unit Economics & Tiers'!D9 | G14: =(E14-F14)/E14 | H14: ='Fixed OpEx'!D17 * IF(14>10, 1.3, IF(14>7, 1.15, 1.0)) | I14: =E14*0.02 + (B14+C14+D14)*0.3 | J14: =E14-F14-H14-I14 | K14: =J14/E14
A15: Month 11 | B15: 370 | C15: 160 | D15: 20 | E15: =B15*'Unit Economics & Tiers'!C7 + C15*'Unit Economics & Tiers'!C8 + D15*'Unit Economics & Tiers'!C9 | F15: =B15*'Unit Economics & Tiers'!D7 + C15*'Unit Economics & Tiers'!D8 + D15*'Unit Economics & Tiers'!D9 | G15: =(E15-F15)/E15 | H15: ='Fixed OpEx'!D17 * IF(15>10, 1.3, IF(15>7, 1.15, 1.0)) | I15: =E15*0.02 + (B15+C15+D15)*0.3 | J15: =E15-F15-H15-I15 | K15: =J15/E15
A16: Month 12 | B16: 460 | C16: 200 | D16: 26 | E16: =B16*'Unit Economics & Tiers'!C7 + C16*'Unit Economics & Tiers'!C8 + D16*'Unit Economics & Tiers'!C9 | F16: =B16*'Unit Economics & Tiers'!D7 + C16*'Unit Economics & Tiers'!D8 + D16*'Unit Economics & Tiers'!D9 | G16: =(E16-F16)/E16 | H16: ='Fixed OpEx'!D17 * IF(16>10, 1.3, IF(16>7, 1.15, 1.0)) | I16: =E16*0.02 + (B16+C16+D16)*0.3 | J16: =E16-F16-H16-I16 | K16: =J16/E16
A17: YEAR 1 CUMULATIVE TOTALS | B17: =SUM(B5:B16) | C17: =SUM(C5:C16) | D17: =SUM(D5:D16) | E17: =SUM(E5:E16) | F17: =SUM(F5:F16) | G17: =(E17-F17)/E17 | H17: =SUM(H5:H16) | I17: =SUM(I5:I16) | J17: =SUM(J5:J16) | K17: =J17/E17
